llm_quick_tools/__init__.py
llm_quick_tools/evaluator.py
llm_quick_tools/mock_llm.py
llm_quick_tools-0.1.2.dist-info/METADATA
llm_quick_tools-0.1.2.dist-info/WHEEL
llm_quick_tools-0.1.2.dist-info/top_level.txt
llm_quick_tools-0.1.2.dist-info/RECORD
